flask_uploads/__init__.py
flask_uploads/exceptions.py
flask_uploads/extensions.py
flask_uploads/flask_uploads.py
flask_uploads/py.typed
flask_uploads/test_helper.py
Flask_Reuploaded-1.4.0.dist-info/LICENSE
Flask_Reuploaded-1.4.0.dist-info/METADATA
Flask_Reuploaded-1.4.0.dist-info/WHEEL
Flask_Reuploaded-1.4.0.dist-info/top_level.txt
Flask_Reuploaded-1.4.0.dist-info/RECORD
